rustme-0.1.35.dist-info/METADATA
rustme-0.1.35.dist-info/WHEEL
rustme/__init__.py
rustme/ame_chunk.py
rustme_rust/__init__.py
rustme_rust/rustme_rust.cp312-win_amd64.pyd
rustme-0.1.35.dist-info/RECORD
