Metadata-Version: 2.4
Name: rustme
Version: 0.1.35
Classifier: Programming Language :: Rust
Classifier: Programming Language :: Python :: Implementation :: CPython
Classifier: Programming Language :: Python :: Implementation :: PyPy
Requires-Dist: numpy >=1.18.0
Requires-Dist: pandas >=1.0.0
Requires-Dist: scipy >=1.4.0
Requires-Dist: statsmodels >=0.12.0
Summary: A Rust-based marginal effects calculator for Probit, callable from Python.
Keywords: rust,python,Marginal effects,pyo3
Author-email: Luke Brosnan <luke.brosnan.cbc@gmail.com>
License: N/A
Requires-Python: >=3.8
